oxeekparser/__init__.py
oxeekparser/cmd_integration.py
oxeekparser/parser.py
oxeekparser-3.4.1.dist-info/LICENSE
oxeekparser-3.4.1.dist-info/METADATA
oxeekparser-3.4.1.dist-info/WHEEL
oxeekparser-3.4.1.dist-info/top_level.txt
oxeekparser-3.4.1.dist-info/RECORD
