Metadata-Version: 2.1
Name: oxeekparser
Version: 3.4.1
Summary: Universal parser with using regex
Home-page: https://github.com/oxeekezy/universal-parser
Author: oxeek
Author-email: workkukin@gmail.com
License: UNKNOWN
Platform: UNKNOWN
Classifier: Programming Language :: Python :: 3.10
Classifier: License :: OSI Approved :: MIT License
Classifier: Operating System :: OS Independent
Requires-Python: >=3.9
License-File: LICENSE
Requires-Dist: selenium (~=4.5.0)
